odoo9_addon_barcodes_generator_partner-9.0.1.0.0.99.dev2-py2.7-nspkg.pth
odoo9_addon_barcodes_generator_partner-9.0.1.0.0.99.dev2.dist-info/DESCRIPTION.rst
odoo9_addon_barcodes_generator_partner-9.0.1.0.0.99.dev2.dist-info/METADATA
odoo9_addon_barcodes_generator_partner-9.0.1.0.0.99.dev2.dist-info/RECORD
odoo9_addon_barcodes_generator_partner-9.0.1.0.0.99.dev2.dist-info/WHEEL
odoo9_addon_barcodes_generator_partner-9.0.1.0.0.99.dev2.dist-info/metadata.json
odoo9_addon_barcodes_generator_partner-9.0.1.0.0.99.dev2.dist-info/namespace_packages.txt
odoo9_addon_barcodes_generator_partner-9.0.1.0.0.99.dev2.dist-info/top_level.txt
odoo_addons/barcodes_generator_partner/README.rst
odoo_addons/barcodes_generator_partner/__init__.py
odoo_addons/barcodes_generator_partner/__openerp__.py
odoo_addons/barcodes_generator_partner/demo/barcode_rule.xml
odoo_addons/barcodes_generator_partner/demo/function.xml
odoo_addons/barcodes_generator_partner/demo/ir_sequence.xml
odoo_addons/barcodes_generator_partner/demo/res_partner.xml
odoo_addons/barcodes_generator_partner/i18n/barcodes_generator_partner.pot
odoo_addons/barcodes_generator_partner/i18n/fr.po
odoo_addons/barcodes_generator_partner/models/__init__.py
odoo_addons/barcodes_generator_partner/models/barcode_rule.py
odoo_addons/barcodes_generator_partner/models/res_partner.py
odoo_addons/barcodes_generator_partner/static/description/icon.png
odoo_addons/barcodes_generator_partner/static/description/res_partner_sequence_generation.png
odoo_addons/barcodes_generator_partner/tests/__init__.py
odoo_addons/barcodes_generator_partner/tests/test_barcodes_generator_partner.py
odoo_addons/barcodes_generator_partner/views/view_res_partner.xml
